mehdiMaze/__init__.py
mehdiMaze/starter.py
mehdiMaze/MazePackage/__init__.py
mehdiMaze/MazePackage/mazeGenerator.py
mehdiMaze/MazePackage/mazeStarter.py
mehdiMaze-1.4.7.dist-info/LICENSE
mehdiMaze-1.4.7.dist-info/METADATA
mehdiMaze-1.4.7.dist-info/WHEEL
mehdiMaze-1.4.7.dist-info/top_level.txt
mehdiMaze-1.4.7.dist-info/RECORD
