Metadata-Version: 2.1
Name: mehdiMaze
Version: 1.4.7
Summary: My first Python package
Author: Mehdi Samee Rad
Author-email: SameeRad@aut.ac.ir
Keywords: python,maze,game,samee,rad,mehdi
Classifier: Development Status :: 3 - Alpha
Classifier: Intended Audience :: Education
Classifier: Programming Language :: Python :: 2
Classifier: Programming Language :: Python :: 3
License-File: LICENSE
Requires-Dist: tabulate
